moduler/__init__.py
moduler/modules/__init__.py
moduler/modules/base.py
moduler/modules/executor.py
moduler/modules/stack.py
moduler/proto/commons.proto
moduler/proto/commons_pb2.py
moduler/proto/commons_pb2.pyi
moduler/proto/commons_pb2_grpc.py
moduler/proto/commons_pb2_grpc.pyi
moduler/proto/service.proto
moduler/proto/service_pb2.py
moduler/proto/service_pb2.pyi
moduler/proto/service_pb2_grpc.py
moduler/proto/service_pb2_grpc.pyi
moduler/utils/__init__.py
moduler/utils/enums.py
moduler/utils/misc.py
moduler-0.0.7.dist-info/LICENSE
moduler-0.0.7.dist-info/METADATA
moduler-0.0.7.dist-info/WHEEL
moduler-0.0.7.dist-info/top_level.txt
moduler-0.0.7.dist-info/RECORD
