Metadata-Version: 2.1
Name: moduler
Version: 0.0.7
Home-page: https://github.com/Babs-Technologies/moduler
Author: Babs Technologies
Author-email: 
License: MIT
Keywords: model adapter,deep learning,machine learning,gpu,distributed computing,pytorch
Classifier: Development Status :: 4 - Beta
Classifier: Intended Audience :: Developers
Classifier: Intended Audience :: Science/Research
Classifier: License :: OSI Approved :: Apache Software License
Classifier: Programming Language :: Python :: 3
Classifier: Programming Language :: Python :: 3.7
Classifier: Programming Language :: Python :: 3.8
Classifier: Programming Language :: Python :: 3.9
Classifier: Programming Language :: Python :: 3.10
Classifier: Topic :: Scientific/Engineering
Classifier: Topic :: Scientific/Engineering :: Mathematics
Classifier: Topic :: Scientific/Engineering :: Artificial Intelligence
Classifier: Topic :: Software Development
Classifier: Topic :: Software Development :: Libraries
Classifier: Topic :: Software Development :: Libraries :: Python Modules
License-File: LICENSE
Requires-Dist: torch >=1.9.0
Requires-Dist: grpcio ==1.60.0
Requires-Dist: numpy ==1.21.2
Requires-Dist: protobuf ==4.25.1
